Metadata-Version: 2.1
Name: listennotes
Version: 0.0.1a1
Summary: search listennotes
Home-page: https://github.com/OpenJarbas/listennotes
Author: JarbasAi
License: UNKNOWN
Platform: UNKNOWN
